README.rst
setup.py
bin/cgdot
cgnet/__init__.py
cgnet.egg-info/PKG-INFO
cgnet.egg-info/SOURCES.txt
cgnet.egg-info/dependency_links.txt
cgnet.egg-info/requires.txt
cgnet.egg-info/top_level.txt